AUTHORS.rst
CONTRIBUTING.rst
HISTORY.rst
LICENSE
MANIFEST.in
README.rst
setup.cfg
setup.py
blocking/__init__.py
blocking/blocking.py
blocking.egg-info/PKG-INFO
blocking.egg-info/SOURCES.txt
blocking.egg-info/dependency_links.txt
blocking.egg-info/not-zip-safe
blocking.egg-info/top_level.txt
test/test_blocking.py