Metadata-Version: 1.1
Name: blocking
Version: 0.1.0
Summary: Stage directions for Python ML projects.
Home-page: https://github.com/yngtodd/blocking
Author: Todd Young
Author-email: youngmt1@ornl.gov
License: MIT
Keywords: blocking
Platform: UNKNOWN
Classifier: Development Status :: 2 - Pre-Alpha
Classifier: Intended Audience :: Developers
Classifier: License :: OSI Approved :: MIT License
Classifier: Natural Language :: English
Classifier: Programming Language :: Python :: 3.6
Classifier: Programming Language :: Python :: Implementation :: PyPy
